ChorusFruit2/__init__.py
ChorusFruit2/__main__.py
ChorusFruit2/core.py
ChorusFruit2/style.py
ChorusFruit2-0.0.1.dist-info/LICENSE
ChorusFruit2-0.0.1.dist-info/LICENSE.txt
ChorusFruit2-0.0.1.dist-info/METADATA
ChorusFruit2-0.0.1.dist-info/WHEEL
ChorusFruit2-0.0.1.dist-info/top_level.txt
ChorusFruit2-0.0.1.dist-info/RECORD
