Metadata-Version: 2.1
Name: ChorusFruit2
Version: 0.0.1
Summary: an Easy way to Make TUIs
Author: mani.f
Project-URL: Homepage, https://github.com/manifarizi/ChorusFruit2
Project-URL: Bug Tracker, https://github.com/manifarizi/ChorusFruit2/issues
Classifier: Programming Language :: Python :: 3
Classifier: License :: OSI Approved :: MIT License
Classifier: Operating System :: OS Independent
Requires-Python: >=3.7
License-File: LICENSE
License-File: LICENSE.txt
